byte_sleuth/LICENCE
byte_sleuth/NOTICE.md
byte_sleuth/README.md
byte_sleuth/__init__.py
byte_sleuth/byte_sleuth.py
byte_sleuth/icon.png
byte_sleuth/icon.svg
bytesleuth-1.0.5.dist-info/METADATA
bytesleuth-1.0.5.dist-info/WHEEL
bytesleuth-1.0.5.dist-info/entry_points.txt
bytesleuth-1.0.5.dist-info/licenses/LICENCE
bytesleuth-1.0.5.dist-info/licenses/NOTICE.md
bytesleuth-1.0.5.dist-info/RECORD
