Metadata-Version: 2.4
Name: byteSleuth
Version: 1.0.5
Summary: A Python package for detecting hidden Unicode and ASCII characters.
Project-URL: Homepage, https://github.com/faelmori/byte_sleuth
Project-URL: Documentation, https://github.com/faelmori/byte_sleuth/docs
Project-URL: Repository, https://github.com/faelmori/byte_sleuth
Project-URL: Bug Tracker, https://github.com/faelmori/byte_sleuth/issues
Author-email: Rafael Mori <faelmori@gmail.com>
Maintainer-email: Rafael Mori <faelmori@gmail.com>
License: MIT
License-File: LICENCE
License-File: NOTICE.md
Keywords: ascii,data validation,logging,security,text analysis,unicode
Classifier: Development Status :: 4 - Beta
Classifier: Intended Audience :: Developers
Classifier: Intended Audience :: Information Technology
Classifier: License :: OSI Approved :: MIT License
Classifier: Operating System :: OS Independent
Classifier: Programming Language :: Python :: 3
Classifier: Topic :: Software Development :: Libraries
Requires-Python: >=3.7
Requires-Dist: flake8
Requires-Dist: pytest
Requires-Dist: rich>=13.3.5
Provides-Extra: dev
Requires-Dist: black; extra == 'dev'
Requires-Dist: mypy; extra == 'dev'
Provides-Extra: docs
Requires-Dist: mkdocs; extra == 'docs'
Provides-Extra: test
Requires-Dist: pytest; extra == 'test'
